pyoxr
