Metadata-Version: 1.0
Name: pyoxr
Version: 1.4
Summary: Python client for openexchangerates.org
Home-page: https://github.com/retargetapp/pyoxr
Author: RetargetApp
Author-email: UNKNOWN
License: UNKNOWN
Keywords: openexchangerate,client,api
Platform: UNKNOWN
